[
  {
    "category": "로아 직업",
    "suggestions": [
      "워로드",
      "버서커",
      "디스트로이어",
      "홀리나이트",
      "배틀마스터",
      "인파이터",
      "기공사",
      "창술사",
      "데빌헌터",
      "블래스터",
      "호크아이",
      "스카우터",
      "바드",
      "서머너",
      "아르카나",
      "블레이드",
      "데모닉",
      "리퍼",
      "건슬리어",
      "스트라이커"
    ]
  },
  {
    "category": "로아 캐릭터",
    "suggestions": [
      "아만",
      "실리안",
      "웨이",
      "샨디",
      "진저웨일",
      "아제나",
      "이난나",
      "바훈투르",
      "니나브",
      "카단",
      "카마인",
      "발탄",
      "쿠크세이튼",
      "비아키스",
      "일리아칸",
      "아브렐슈드",
      "카멘",
      "루테란",
      "시엔",
      "갈라투르",
      "베아트리스",
      "가디언 루",
      "알레그로",
      "검은이빨",
      "모카모카",
      "바스티안",
      "사샤",
      "마리 파우렌츠",
      "기술관 카인",
      "진 매드닉",
      "라하르트",
      "아나벨",
      "운다트",
      "케이사르",
      "사이카",
      "칼도르",
      "페데리코",
      "아델",
      "에아달린",
      "에르제베트",
      "크리스틴",
      "칼바서스",
      "니아",
      "샤나",
      "알비온",
      "타나토스",
      "천둥날개",
      "슈헤리트",
      "로나운",
      "자간",
      "하백",
      "반다",
      "진화의 군주 카인",
      "지그문트",
      "나크라세나",
      "레바노스",
      "베르투스",
      "크로마니움",
      "헬가이아",
      "빙결의 레기오로스",
      "어둠의 레기오로스",
      "에페르니아",
      "벨크루제",
      "카이슈르",
      "루메루스",
      "우르닐",
      "칼벤투스",
      "용암 크로마니움",
      "중갑 나크라세나",
      "홍염의 요호",
      "혹한의 헬가이아",
      "타이탈로스",
      "흑야의 요호",
      "벨가누스",
      "칼엘리고스",
      "아카테스",
      "이그렉시온",
      "미스틱",
      "카이슈테르",
      "엘버하스틱",
      "아르카디아",
      "아르고스",
      "데스칼루다",
      "쿤겔라니움",
      "바루투",
      "네리아(레온하트)",
      "천둥",
      "미한",
      "하셀링크",
      "네리아(루테란 성)",
      "세리아",
      "자히아",
      "리게아스",
      "하울로크",
      "칼스 모론토",
      "네리아(갈기파도)",
      "토토마",
      "파한",
      "네리아(아르데타인)",
      "바에단",
      "시안",
      "기드온",
      "페일린",
      "엘레노아",
      "아벤",
      "게르디아",
      "오렐다",
      "네리아(웨대한 성)",
      "비올레",
      "굴딩",
      "판다 푸푸",
      "샐리 자하라",
      "리루",
      "나기",
      "하이거",
      "제레온",
      "신디",
      "네리아(베른 남부)",
      "소금거인",
      "로블롬",
      "윌리윌리",
      "거신 카스피엘",
      "아크의 수호자 오셀",
      "만포",
      "미령",
      "원포",
      "길달",
      "절망의 레키엘",
      "도철",
      "혼재의 추오",
      "시그나투스",
      "에스",
      "제이",
      "타르실라",
      "가룸",
      "프록시마",
      "에라스모",
      "브리아레오스",
      "고르카그로스",
      "수신 아포라스",
      "실험체 타르마쿰",
      "솔 그랑데",
      "변절자 제페토",
      "아이히만 박사",
      "아드린느",
      "세토",
      "스텔라",
      "루기네",
      "두키킹"
    ]
  },
  {
    "category": "과일",
    "suggestions": [
      "doldding",
      "Zzombie",
      "고기괵",
      "고대콩",
      "냉참치",
      "시체",
      "연방",
      "핫징",
      "김과자",
      "륭룡륭이",
      "사쿠",
      "CREO",
      "제로백피시방"
    ]
  },
  {
    "category": "과일",
    "suggestions": [
      "체리",
      "자두",
      "딸기",
      "오렌지",
      "사과",
      "키위",
      "메론",
      "포도",
      "버찌",
      "야자",
      "복숭아",
      "레몬",
      "수박",
      "망고",
      "자몽",
      "살구",
      "리치",
      "모과",
      "거봉",
      "유자",
      "매실",
      "코코넛",
      "바나나",
      "석류",
      "감",
      "두리안",
      "아보카도",
      "구아바",
      "무화과",
      "파파야",
      "블루베리",
      "파인애플",
      "한라봉",
      "샤인머스캣",
      "레드향",
      "앵두",
      "제주감귤"
    ]
  }
]
